{
  "type": "FeatureCollection",
  "features": [
    {
      "type": "Feature",
      "properties": {
        "info_address": "600 Highland Ave",
        "info_city": "Madison",
        "info_state": "WI",
        "info_zip": "",
        "info_country": "",
        "info_notes": "93-'95",
        "info_lastName": "Gallagher",
        "info_maidenName": "",
        "info_firstName": "Catherine",
        "info_middleName": "",
        "info_intern": "",
        "info_resident": "r",
        "info_fellow": "f",
        "info_fellowshipSection": "",
        "info_honoraryFellow": "",
        "info_formerFaculty": "",
        "info_facultySection": "",
        "info_residencyBegin": "",
        "info_residencyEnd": "",
        "info_fellowshipBegin": "",
        "info_fellowshipEnd": "",
        "info_institution": "University of Wisconsin Department of Neurology",
        "info_position": "",
        "info_count": 1,
        "info_resDate": 1900,
        "info_felDate": 1900,
        "info_date": 1995,
        "info_status": "rf"
      },
      "geometry": {
        "type": "Point",
        "coordinates": [
          -89.4290999,
          43.077
        ]
      }
    }
  ]
}