{
  "type": "FeatureCollection",
  "features": [
    {
      "type": "Feature",
      "properties": {
        "info_address": "2941 South Ridge Road",
        "info_city": "Green Bay",
        "info_state": "WI",
        "info_zip": 54304,
        "info_country": "",
        "info_notes": "",
        "info_lastName": "Smyth",
        "info_maidenName": "",
        "info_firstName": "Ronan",
        "info_middleName": "",
        "info_intern": "",
        "info_resident": "r",
        "info_fellow": "f",
        "info_fellowshipSection": "",
        "info_honoraryFellow": "",
        "info_formerFaculty": "",
        "info_facultySection": "",
        "info_residencyBegin": "",
        "info_residencyEnd": "",
        "info_fellowshipBegin": "",
        "info_fellowshipEnd": "",
        "info_institution": "Green Bay Radiology",
        "info_position": "",
        "info_count": 1,
        "info_resDate": 1900,
        "info_felDate": 1900,
        "info_date": 1998,
        "info_status": "rf"
      },
      "geometry": {
        "type": "Point",
        "coordinates": [
          -88.0862928,
          44.4721866
        ]
      }
    }
  ]
}